orbro_sdk/__init__.py
orbro_sdk/app.py
orbro_sdk/async_client.py
orbro_sdk/constants.py
orbro_sdk/datastore.py
orbro_sdk/exceptions.py
orbro_sdk/models.py
orbro_sdk/util.py
orbro_sdk/fastapi/api_router/__init__.py
orbro_sdk/fastapi/api_router/lifecycle.py
orbro_sdk/fastapi/dependencies/auth.py
orbro_sdk/fastapi/dependencies/client.py
orbro_sdk/fastapi/dependencies/database.py
orbro_sdk/fastapi/middleware/__init__.py
orbro_sdk/fastapi/middleware/auth.py
orbro_sdk/fastapi/middleware/database.py
orbro_python_sdk-0.23.dist-info/LICENSE
orbro_python_sdk-0.23.dist-info/METADATA
orbro_python_sdk-0.23.dist-info/WHEEL
orbro_python_sdk-0.23.dist-info/top_level.txt
orbro_python_sdk-0.23.dist-info/RECORD
