Metadata-Version: 2.1
Name: orbro-python-sdk
Version: 0.23
Summary: ORBRO-Connect SDK for Python(FastAPI/Flask)
Home-page: https://www.notion.so/ORBRO-Connect-7065dd4435264beebdeb52c7f7408820
Author: ORBRO
Author-email: platform.dev@kong-tech.com
License: Apache License 2.0
Keywords: orbro connect iot digitaltwin rtls
Platform: UNKNOWN
Classifier: Development Status :: 4 - Beta
Classifier: Intended Audience :: Developers
Classifier: Programming Language :: Python :: 3.7
Classifier: License :: OSI Approved :: Apache Software License
Classifier: Operating System :: OS Independent
Classifier: Topic :: Software Development :: Libraries
Classifier: Topic :: Utilities
Classifier: Topic :: Office/Business
Classifier: Framework :: FastAPI
Requires-Python: >=3.7
Requires-Dist: SQLAlchemy (==1.4.27)
Requires-Dist: pydantic (!=1.7,!=1.7.1,!=1.7.2,!=1.7.3,!=1.8,!=1.8.1,<2.0.0,>=1.6.2)
Requires-Dist: redis (>=3.5.3)
Requires-Dist: PyJWT (==2.3.0)
Requires-Dist: httpx (==0.19.0)
